MANIFEST.in
README
setup.py
simple_translation/__init__.py
simple_translation/actions.py
simple_translation/admin.py
simple_translation/forms.py
simple_translation/middleware.py
simple_translation/models.py
simple_translation/tests.py
simple_translation/translation_pool.py
simple_translation/utils.py
simple_translation/widgets.py
simple_translation.egg-info/PKG-INFO
simple_translation.egg-info/SOURCES.txt
simple_translation.egg-info/dependency_links.txt
simple_translation.egg-info/not-zip-safe
simple_translation.egg-info/top_level.txt
simple_translation/locale/en/LC_MESSAGES/django.po
simple_translation/locale/nb/LC_MESSAGES/django.mo
simple_translation/locale/nb/LC_MESSAGES/django.po
simple_translation/static/simple_translation/widget.css
simple_translation/templates/simple_translation/language_choices.html
simple_translation/templatetags/__init__.py
simple_translation/templatetags/simple_translation_tags.py
simple_translation/test/__init__.py
simple_translation/test/run_tests.py
simple_translation/test/testcases.py
simple_translation/test/testapp/__init__.py
simple_translation/test/testapp/admin.py
simple_translation/test/testapp/models.py
simple_translation/test/testapp/no_translated_urls.py
simple_translation/test/testapp/simple_translate.py
simple_translation/test/testapp/translated_urls.py
simple_translation/test/testapp/urls.py
simple_translation/test/testapp/templates/testapp/entrytitle_archive.html
simple_translation/test/testapp/templates/testapp/entrytitle_archive_month.html
simple_translation/test/testapp/templates/testapp/entrytitle_archive_year.html
simple_translation/test/testapp/templates/testapp/entrytitle_day.html
simple_translation/test/testapp/templates/testapp/entrytitle_detail.html
simple_translation/test/testapp/templates/testapp/entrytitle_list.html