Metadata-Version: 1.0
Name: simple-translation
Version: 0.8.6
Summary: This is a translation app/plugin with support for django-cms 2.1 plugins in the admin
Home-page: http://github.com/fivethreeo/simple-translation/
Author: Oyvind Saltvik
Author-email: oyvind.saltvik@gmail.com
License: UNKNOWN
Platform: UNKNOWN
Classifier: Development Status :: 3 - Alpha
Classifier: Environment :: Web Environment
Classifier: Intended Audience :: Developers
Classifier: License :: OSI Approved :: BSD License
Classifier: Operating System :: OS Independent
Classifier: Programming Language :: Python
Classifier: Framework :: Django
